CausalEstimate/__init__.py
CausalEstimate/_version.py
CausalEstimate/core/bootstrap.py
CausalEstimate/core/logging.py
CausalEstimate/core/multi_estimator.py
CausalEstimate/datasets/__init__.py
CausalEstimate/datasets/binary.py
CausalEstimate/estimators/__init__.py
CausalEstimate/estimators/aipw.py
CausalEstimate/estimators/base.py
CausalEstimate/estimators/ipw.py
CausalEstimate/estimators/matching.py
CausalEstimate/estimators/tmle.py
CausalEstimate/estimators/functional/aipw.py
CausalEstimate/estimators/functional/ipw.py
CausalEstimate/estimators/functional/matching.py
CausalEstimate/estimators/functional/tmle.py
CausalEstimate/estimators/functional/tmle_att.py
CausalEstimate/estimators/functional/utils.py
CausalEstimate/estimators/functional/variance.py
CausalEstimate/filter/filter.py
CausalEstimate/filter/propensity.py
CausalEstimate/matching/assignment.py
CausalEstimate/matching/distance.py
CausalEstimate/matching/helpers.py
CausalEstimate/matching/matching.py
CausalEstimate/simulation/binary_simulation.py
CausalEstimate/stats/stats.py
CausalEstimate/stats/utils.py
CausalEstimate/utils/checks.py
CausalEstimate/utils/constants.py
CausalEstimate/utils/extract.py
CausalEstimate/utils/logging.py
CausalEstimate/utils/utils.py
CausalEstimate/vis/__init__.py
CausalEstimate/vis/plotting.py
causalestimate-0.10.1.dist-info/METADATA
causalestimate-0.10.1.dist-info/WHEEL
causalestimate-0.10.1.dist-info/top_level.txt
causalestimate-0.10.1.dist-info/RECORD
