Metadata-Version: 2.4
Name: CausalEstimate
Version: 0.10.1
Summary: A library for estimates of causal effects.
Author-email: Kiril Klein <kikl@di.ku.dk>
Project-URL: Source, https://github.com/kirilklein/CausalEstimate.git
Classifier: Development Status :: 4 - Beta
Classifier: Intended Audience :: Science/Research
Classifier: Topic :: Scientific/Engineering :: Information Analysis
Classifier: Programming Language :: Python :: 3
Classifier: License :: OSI Approved :: MIT License
Classifier: Operating System :: OS Independent
Requires-Python: >=3.9
Requires-Dist: pandas
Requires-Dist: numpy
Requires-Dist: scikit-learn
Requires-Dist: scipy
Requires-Dist: statsmodels
Requires-Dist: tqdm
Provides-Extra: dev
Requires-Dist: pytest; extra == "dev"
Requires-Dist: black; extra == "dev"
Requires-Dist: flake8; extra == "dev"
Provides-Extra: plotting
Requires-Dist: matplotlib; extra == "plotting"
Requires-Dist: seaborn; extra == "plotting"
Requires-Dist: plotly; extra == "plotting"
